ZetcodeQitaJiaochengChuyiFix1/README.md
ZetcodeQitaJiaochengChuyiFix1/__init__.py
ZetcodeQitaJiaochengChuyiFix1/__main__.py
ZetcodeQitaJiaochengChuyiFix1/file.epub
ZetcodeQitaJiaochengChuyiFix1/index.html
ZetcodeQitaJiaochengChuyiFix1/css/__init__.py
ZetcodeQitaJiaochengChuyiFix1/css/annotations.css
ZetcodeQitaJiaochengChuyiFix1/css/main.css
ZetcodeQitaJiaochengChuyiFix1/css/normalize.css
ZetcodeQitaJiaochengChuyiFix1/css/popup.css
ZetcodeQitaJiaochengChuyiFix1/font/__init__.py
ZetcodeQitaJiaochengChuyiFix1/font/fontello.eot
ZetcodeQitaJiaochengChuyiFix1/font/fontello.svg
ZetcodeQitaJiaochengChuyiFix1/font/fontello.ttf
ZetcodeQitaJiaochengChuyiFix1/font/fontello.woff
ZetcodeQitaJiaochengChuyiFix1/img/__init__.py
ZetcodeQitaJiaochengChuyiFix1/img/annotator-glyph-sprite.png
ZetcodeQitaJiaochengChuyiFix1/img/annotator-icon-sprite.png
ZetcodeQitaJiaochengChuyiFix1/img/apple-touch-icon.png
ZetcodeQitaJiaochengChuyiFix1/img/cancelfullscreen.png
ZetcodeQitaJiaochengChuyiFix1/img/close.png
ZetcodeQitaJiaochengChuyiFix1/img/fullscreen.png
ZetcodeQitaJiaochengChuyiFix1/img/loader.gif
ZetcodeQitaJiaochengChuyiFix1/img/menu-icon.png
ZetcodeQitaJiaochengChuyiFix1/img/save.png
ZetcodeQitaJiaochengChuyiFix1/img/saved.png
ZetcodeQitaJiaochengChuyiFix1/img/settings-s.png
ZetcodeQitaJiaochengChuyiFix1/img/settings.png
ZetcodeQitaJiaochengChuyiFix1/img/star.png
ZetcodeQitaJiaochengChuyiFix1/js/__init__.py
ZetcodeQitaJiaochengChuyiFix1/js/epub.js
ZetcodeQitaJiaochengChuyiFix1/js/epub.min.js
ZetcodeQitaJiaochengChuyiFix1/js/epub.min.map
ZetcodeQitaJiaochengChuyiFix1/js/hooks.min.js
ZetcodeQitaJiaochengChuyiFix1/js/hooks.min.map
ZetcodeQitaJiaochengChuyiFix1/js/reader.js
ZetcodeQitaJiaochengChuyiFix1/js/reader.js.map
ZetcodeQitaJiaochengChuyiFix1/js/reader.min.js
ZetcodeQitaJiaochengChuyiFix1/js/reader.min.map
ZetcodeQitaJiaochengChuyiFix1/js/hooks/__init__.py
ZetcodeQitaJiaochengChuyiFix1/js/hooks/extensions/__init__.py
ZetcodeQitaJiaochengChuyiFix1/js/hooks/extensions/highlight.js
zetcode_qita_jiaocheng_chuyi_fix1-2025.3.24.0.dist-info/METADATA
zetcode_qita_jiaocheng_chuyi_fix1-2025.3.24.0.dist-info/WHEEL
zetcode_qita_jiaocheng_chuyi_fix1-2025.3.24.0.dist-info/entry_points.txt
zetcode_qita_jiaocheng_chuyi_fix1-2025.3.24.0.dist-info/top_level.txt
zetcode_qita_jiaocheng_chuyi_fix1-2025.3.24.0.dist-info/RECORD
